AUTHORS
CONTRIBUTING.rst
INSTALL
LICENSE
MANIFEST.in
README.rst
setup.cfg
setup.py
Pootle.egg-info/PKG-INFO
Pootle.egg-info/SOURCES.txt
Pootle.egg-info/dependency_links.txt
Pootle.egg-info/entry_points.txt
Pootle.egg-info/not-zip-safe
Pootle.egg-info/requires.txt
Pootle.egg-info/top_level.txt
docs/Makefile
docs/conf.py
docs/contents.rst.inc
docs/faq.rst
docs/icons.rst.inc
docs/index.rst
docs/license.rst
docs/make.bat
docs/_build/html/.buildinfo
docs/_build/html/faq.html
docs/_build/html/genindex.html
docs/_build/html/index.html
docs/_build/html/license.html
docs/_build/html/objects.inv
docs/_build/html/search.html
docs/_build/html/searchindex.js
docs/_build/html/_images/accessing_admin_interface.png
docs/_build/html/_images/accessing_team.png
docs/_build/html/_images/add_project_button.png
docs/_build/html/_images/add_project_form.png
docs/_build/html/_images/add_team_member.png
docs/_build/html/_images/altsrc.png
docs/_build/html/_images/asciinema_org_92502.png
docs/_build/html/_images/critical_errors.png
docs/_build/html/_images/enable_new_tp_through_admin_UI.png
docs/_build/html/_images/failing-checks.png
docs/_build/html/_images/icon-accept-white.png
docs/_build/html/_images/icon-accept.png
docs/_build/html/_images/icon-arrow-down.png
docs/_build/html/_images/icon-arrow-up.png
docs/_build/html/_images/icon-asc.gif
docs/_build/html/_images/icon-ascdesc.gif
docs/_build/html/_images/icon-back.png
docs/_build/html/_images/icon-block-muted.png
docs/_build/html/_images/icon-block.png
docs/_build/html/_images/icon-caighdean-translate.png
docs/_build/html/_images/icon-collapse-stats.png
docs/_build/html/_images/icon-comment-add.png
docs/_build/html/_images/icon-comment-user.png
docs/_build/html/_images/icon-copy.png
docs/_build/html/_images/icon-desc.gif
docs/_build/html/_images/icon-download.png
docs/_build/html/_images/icon-error.png
docs/_build/html/_images/icon-expand-stats.png
docs/_build/html/_images/icon-external-link.png
docs/_build/html/_images/icon-file.png
docs/_build/html/_images/icon-folder-parent.png
docs/_build/html/_images/icon-folder.png
docs/_build/html/_images/icon-github.png
docs/_build/html/_images/icon-google-translate.png
