Metadata-Version: 1.1
Name: Pootle
Version: 2.8.2
Summary: An online collaborative localization tool.
Home-page: http://pootle.translatehouse.org
Author: Translate
Author-email: dev@translate.org.za
License: GNU General Public License 3 or later (GPLv3+)
Download-URL: https://github.com/translate/pootle/releases/tag/2.8.2
Platform: any
Classifier: Development Status :: 5 - Production/Stable
Classifier: Environment :: Web Environment
Classifier: Framework :: Django
Classifier: Framework :: Django :: 1.10
Classifier: Intended Audience :: Developers
Classifier: Intended Audience :: End Users/Desktop
Classifier: Intended Audience :: Information Technology
Classifier: License :: OSI Approved :: GNU General Public License v3 or later (GPLv3+)
Classifier: Operating System :: OS Independent
Classifier: Operating System :: Unix
Classifier: Programming Language :: JavaScript
Classifier: Programming Language :: Python
Classifier: Programming Language :: Python :: 2.7
Classifier: Topic :: Software Development :: Localization
Classifier: Topic :: Text Processing :: Linguistic
